py9pfactotum/__init__.py
py9pfactotum/client.py
py9pfactotum/errors.py
py9pfactotum/keyring.py
py9pfactotum/util.py
py9pfactotum/_vendor/LICENSE
py9pfactotum/_vendor/__init__.py
py9pfactotum/_vendor/py9p/__init__.py
py9pfactotum/_vendor/py9p/fuse9p.py
py9pfactotum/_vendor/py9p/pki.py
py9pfactotum/_vendor/py9p/py9p.py
py9pfactotum/_vendor/py9p/utils.py
py9pfactotum-0.1.1.dist-info/entry_points.txt
py9pfactotum-0.1.1.dist-info/WHEEL
py9pfactotum-0.1.1.dist-info/METADATA
py9pfactotum-0.1.1.dist-info/RECORD
