Metadata-Version: 2.1
Name: py9pfactotum
Version: 0.1.1
Summary: The factotum module implements a plan9port's auth(3) library.
Author-email: Daniel Moch <daniel@danielmoch.com>
Requires-Python: >=3.9
Classifier: Development Status :: 3 - Alpha
Classifier: Intended Audience :: Developers
Classifier: License :: OSI Approved :: ISC License (ISCL)
Classifier: License :: OSI Approved :: MIT License
Classifier: Operating System :: POSIX
Classifier: Programming Language :: Python :: 3
Classifier: Programming Language :: Python :: 3 :: Only
Requires-Dist: flake8 ; extra == "dev"
Requires-Dist: flit ; extra == "dev"
Requires-Dist: keyring ; extra == "dev"
Requires-Dist: mypy ; extra == "dev"
Project-URL: Home, https://github.com/djmoch/py9pfactotum
Provides-Extra: dev
